homeassistant/__init__.py
homeassistant/__main__.py
homeassistant/auth.py
homeassistant/bootstrap.py
homeassistant/config.py
homeassistant/config_entries.py
homeassistant/const.py
homeassistant/core.py
homeassistant/data_entry_flow.py
homeassistant/exceptions.py
homeassistant/loader.py
homeassistant/monkey_patch.py
homeassistant/package_constraints.txt
homeassistant/remote.py
homeassistant/requirements.py
homeassistant/setup.py
homeassistant/auth/__init__.py
homeassistant/auth/auth_store.py
homeassistant/auth/const.py
homeassistant/auth/models.py
homeassistant/auth/util.py
homeassistant/auth/mfa_modules/__init__.py
homeassistant/auth/mfa_modules/insecure_example.py
homeassistant/auth/mfa_modules/notify.py
homeassistant/auth/mfa_modules/totp.py
homeassistant/auth/providers/__init__.py
homeassistant/auth/providers/homeassistant.py
homeassistant/auth/providers/insecure_example.py
homeassistant/auth/providers/legacy_api_password.py
homeassistant/auth/providers/trusted_networks.py
homeassistant/auth_providers/__init__.py
homeassistant/auth_providers/homeassistant.py
homeassistant/auth_providers/insecure_example.py
homeassistant/auth_providers/legacy_api_password.py
homeassistant/components/__init__.py
homeassistant/components/abode.py
homeassistant/components/alarmdecoder.py
homeassistant/components/alert.py
homeassistant/components/amcrest.py
homeassistant/components/android_ip_webcam.py
homeassistant/components/apcupsd.py
homeassistant/components/api.py
homeassistant/components/apple_tv.py
homeassistant/components/aqualogic.py
homeassistant/components/arduino.py
homeassistant/components/arlo.py
homeassistant/components/asterisk_mbox.py
homeassistant/components/august.py
homeassistant/components/axis.py
homeassistant/components/bbb_gpio.py
homeassistant/components/blink.py
homeassistant/components/bloomsky.py
homeassistant/components/browser.py
homeassistant/components/canary.py
homeassistant-0.80.1.dist-info/LICENSE.txt
homeassistant-0.80.1.dist-info/METADATA
homeassistant-0.80.1.dist-info/RECORD
homeassistant-0.80.1.dist-info/WHEEL
homeassistant-0.80.1.dist-info/entry_points.txt
homeassistant-0.80.1.dist-info/top_level.txt
