Metadata-Version: 2.1
Name: homeassistant
Version: 0.80.1
Summary: Open-source home automation platform running on Python 3.
Home-page: https://home-assistant.io/
Author: The Home Assistant Authors
Author-email: hello@home-assistant.io
License: Apache License 2.0
Download-URL: https://github.com/home-assistant/home-assistant/archive/0.80.1.zip
Project-URL: Bug Reports, https://github.com/home-assistant/home-assistant/issues
Project-URL: Dev Docs, https://developers.home-assistant.io/
Project-URL: Discord, https://discordapp.com/invite/c5DvZ4e
Project-URL: Forum, https://community.home-assistant.io/
Keywords: home,automation
Platform: any
Classifier: Development Status :: 4 - Beta
Classifier: Intended Audience :: End Users/Desktop
Classifier: Intended Audience :: Developers
Classifier: License :: OSI Approved :: Apache Software License
Classifier: Operating System :: OS Independent
Classifier: Programming Language :: Python :: 3.5
Classifier: Programming Language :: Python :: 3.6
Classifier: Programming Language :: Python :: 3.7
Classifier: Topic :: Home Automation
Requires-Python: >=3.5.3
Requires-Dist: aiohttp (==3.4.4)
Requires-Dist: astral (==1.6.1)
Requires-Dist: async-timeout (==3.0.0)
Requires-Dist: attrs (==18.2.0)
Requires-Dist: bcrypt (==3.1.4)
Requires-Dist: certifi (>=2018.04.16)
Requires-Dist: jinja2 (>=2.10)
Requires-Dist: PyJWT (==1.6.4)
Requires-Dist: cryptography (==2.3.1)
Requires-Dist: pip (>=8.0.3)
Requires-Dist: pytz (>=2018.04)
Requires-Dist: pyyaml (<4,>=3.13)
Requires-Dist: requests (==2.19.1)
Requires-Dist: voluptuous (==0.11.5)
Requires-Dist: voluptuous-serialize (==2.0.0)
